md_head_num/__init__.py
md_head_num/MdHeadNum.py
md_head_num-0.1.1.dist-info/METADATA
md_head_num-0.1.1.dist-info/WHEEL
md_head_num-0.1.1.dist-info/RECORD
