Metadata-Version: 2.3
Name: md_head_num
Version: 0.1.1
Summary: get the numbering at markdown file
License: MIT
Author: kh.cha
Author-email: star2kis@nate.com
Requires-Python: >=3.9
Classifier: License :: OSI Approved :: MIT License
Classifier: Programming Language :: Python :: 3
Classifier: Programming Language :: Python :: 3.9
Classifier: Programming Language :: Python :: 3.10
Classifier: Programming Language :: Python :: 3.11
Classifier: Programming Language :: Python :: 3.12
Classifier: Programming Language :: Python :: 3.13
